Ripple Carry Adder/fa.v
module fa  (
    input A,B,Cin, output S,C
);
assign S = A^B^Cin;
assign C = (A&B) |(B&Cin) |(A&Cin);
    
endmodule

Carry Select Adder/rca.v
`include "fa.v"
module rca(
    input [3:0] A, input [3:0] B, input Cin, output [3:0] S, output Cout
);
    wire [2:0]C;

    fa M1(.A(A[0]), .B(B[0]), .Cin(Cin), .S(S[0]), .C(C[0]));
    fa M2(.A(A[1]), .B(B[1]), .Cin(C[0]), .S(S[1]), .C(C[1]));
    fa M3(.A(A[2]), .B(B[2]), .Cin(C[1]), .S(S[2]), .C(C[2]));
    fa M4(.A(A[3]), .B(B[3]), .Cin(C[2]), .S(S[3]), .C(Cout));

endmodule

carry save adder/csa.v
`include "rca.v"

module csa(
    input [3:0] a,b,c,d, output [4:0]sum, output cout
    );
  wire [3:0] s0,s1;
  wire [3:0] c0, c1;

fa M1( .A(a[0]), .B(b[0]), .Cin(c[0]), .S(s0[0]), .C(c0[0]));
fa M2( .A(a[1]), .B(b[1]), .Cin(c[1]), .S(s0[1]), .C(c0[1]));
fa M3( .A(a[2]), .B(b[2]), .Cin(c[2]), .S(s0[2]), .C(c0[2]));
fa M4( .A(a[3]), .B(b[3]), .Cin(c[3]), .S(s0[3]), .C(c0[3]));

fa M5( .A(d[0]), .B(s0[0]), .Cin(1'b0), .S(sum[0]), .C(c1[0]));
fa M6( .A(d[1]), .B(s0[1]), .Cin(c0[0]), .S(s1[0]), .C(c1[1]));
fa M7( .A(d[2]), .B(s0[2]), .Cin(c0[1]), .S(s1[1]), .C(c1[2]));
fa M8( .A(d[3]), .B(s0[3]), .Cin(c0[2]), .S(s1[2]), .C(c1[3]));

rca M9(.A(c1[3:0]),.B({c0[3],s1[2:0]}), .Cin(1'b0),.S(sum[4:1]), .Cout(cout));

endmodule

carry save adder/tb.v
module tb;
wire [4:0] sum;//output
wire cout;//output
reg [3:0] a,b,c,d;//input
 
 csa uut(
.a(a),
.b(b),
.c(c),
 .d(d),
.sum(sum),
.cout(cout));
 
initial begin
$dumpfile("output.vcd");
$dumpvars(0,tb);
$display($time, " << Starting the Simulation >>");
     a=0; b=0; c=0; d=0;
  #100 a= 10; b=0; c=0; d=0;
  #100 a= 10; b=10; c=0; d=0;
  #100 a= 4; b=6; c=12; d=0;
  #100 a= 11; b=2; c=4; d=7;
  #100 a= 20; b=0; c=20; d=0;
  #100 a= 12; b=5; c=10; d=10;
  #100 a= 7; b=6; c=12; d=8;
  #100 a= 15; b=15; c=15; d=15;
 
end
 
initial
  $monitor("A=%b, B=%b, C=%b,D=%b,Sum= %b, Cout=%b",a,b,c,d,sum,cout);
endmodule

carry save adder/output.vcd
$date
	Tue Jan 03 19:02:59 2023
$end
$version
	Icarus Verilog
$end
$timescale
	1s
$end
$scope module tb $end
$var wire 5 ! sum [4:0] $end
$var wire 1 " cout $end
$var reg 4 # a [3:0] $end
$var reg 4 $ b [3:0] $end
$var reg 4 % c [3:0] $end
$var reg 4 & d [3:0] $end
$scope module uut $end
$var wire 4 ' a [3:0] $end
$var wire 4 ( b [3:0] $end
$var wire 4 ) c [3:0] $end
$var wire 4 * d [3:0] $end
$var wire 5 + sum [4:0] $end
$var wire 4 , s1 [3:0] $end
$var wire 4 - s0 [3:0] $end
$var wire 1 " cout $end
$var wire 4 . c1 [3:0] $end
$var wire 4 / c0 [3:0] $end
$scope module M1 $end
$var wire 1 0 A $end
$var wire 1 1 B $end
$var wire 1 2 C $end
$var wire 1 3 Cin $end
$var wire 1 4 S $end
$upscope $end
$scope module M2 $end
$var wire 1 5 A $end
$var wire 1 6 B $end
$var wire 1 7 C $end
$var wire 1 8 Cin $end
$var wire 1 9 S $end
$upscope $end
$scope module M3 $end
$var wire 1 : A $end
$var wire 1 ; B $end
$var wire 1 < C $end
$var wire 1 = Cin $end
$var wire 1 > S $end
$upscope $end
$scope module M4 $end
$var wire 1 ? A $end
$var wire 1 @ B $end
$var wire 1 A C $end
$var wire 1 B Cin $end
$var wire 1 C S $end
$upscope $end
$scope module M5 $end
$var wire 1 D A $end
$var wire 1 E B $end
$var wire 1 F C $end
$var wire 1 G Cin $end
$var wire 1 H S $end
$upscope $end
$scope module M6 $end
$var wire 1 I A $end
$var wire 1 J B $end
$var wire 1 K C $end
$var wire 1 L Cin $end
$var wire 1 M S $end
$upscope $end
$scope module M7 $end
$var wire 1 N A $end
$var wire 1 O B $end
$var wire 1 P C $end
$var wire 1 Q Cin $end
$var wire 1 R S $end
$upscope $end
$scope module M8 $end
$var wire 1 S A $end
$var wire 1 T B $end
$var wire 1 U C $end
$var wire 1 V Cin $end
$var wire 1 W S $end
$upscope $end
$scope module M9 $end
$var wire 4 X A [3:0] $end
$var wire 4 Y B [3:0] $end
$var wire 1 Z Cin $end
$var wire 4 [ S [3:0] $end
$var wire 1 " Cout $end
$var wire 3 \ C [2:0] $end
$scope module M1 $end
$var wire 1 ] A $end
$var wire 1 ^ B $end
$var wire 1 _ C $end
$var wire 1 Z Cin $end
$var wire 1 ` S $end
$upscope $end
$scope module M2 $end
$var wire 1 a A $end
$var wire 1 b B $end
$var wire 1 c C $end
$var wire 1 d Cin $end
$var wire 1 e S $end
$upscope $end
$scope module M3 $end
$var wire 1 f A $end
$var wire 1 g B $end
$var wire 1 h C $end
$var wire 1 i Cin $end
$var wire 1 j S $end
$upscope $end
$scope module M4 $end
$var wire 1 k A $end
$var wire 1 l B $end
$var wire 1 " C $end
$var wire 1 m Cin $end
$var wire 1 n S $end
$upscope $end
$upscope $end
$upscope $end
$upscope $end
$enddefinitions $end
$comment Show the parameter values. $end
$dumpall
$end
#0
$dumpvars
0n
0m
0l
0k
0j
0i
0h
0g
0f
0e
0d
0c
0b
0a
0`
0_
0^
0]
b0 \
b0 [
0Z
b0 Y
b0 X
0W
0V
0U
0T
0S
0R
0Q
0P
0O
0N
0M
0L
0K
0J
0I
0H
0G
0F
0E
0D
0C
0B
0A
0@
0?
0>
0=
0<
0;
0:
09
08
07
06
05
04
03
02
01
00
b0 /
b0 .
b0 -
bz000 ,
b0 +
b0 *
b0 )
b0 (
b0 '
b0 &
b0 %
b0 $
b0 #
0"
b0 !
$end
#100
1`
b1010 !
b1010 +
b101 [
1j
1^
1g
b101 Y
1M
bz101 ,
1W
1J
1T
19
b1010 -
1C
15
1?
b1010 #
b1010 '
#200
0`
1e
0j
0^
1b
0g
b10100 !
b10100 +
b1010 [
1n
0M
1R
bz010 ,
0W
1l
1Q
b1010 Y
0J
17
0T
b1010 /
1A
09
b0 -
0C
16
1@
b1010 $
b1010 (
#300
1`
0j
1^
b10110 !
b10110 +
b1011 [
1n
0f
1k
0P
b1000 .
b1000 X
1U
bz011 ,
1M
0l
0Q
b11 Y
1J
07
1V
0A
1O
1T
19
b100 /
1<
1>
b1110 -
1C
1=
1B
1;
0@
05
1:
0?
b1100 %
b1100 )
b110 $
b110 (
b100 #
b100 '
#400
1i
1c
0e
1d
1m
1_
b111 \
1h
1n
0k
1]
1g
0U
0`
b1100 [
1j
1F
1W
0a
1^
1b
1f
1Q
0V
0K
b111 Y
b101 .
b101 X
1P
1E
0J
17
b10 /
0<
b11000 !
b11000 +
0H
1M
bz111 ,
1R
14
b1101 -
09
1D
1I
1N
0B
0;
10
15
0:
1?
b111 &
b111 *
b100 %
b100 )
b10 $
b10 (
b1011 #
b1011 '
#500
0n
0m
0h
0d
0i
0_
b0 \
0c
0f
b100 [
0e
0P
0]
0^
0b
0Q
b0 .
b0 X
0F
b100 Y
0E
07
0O
1V
0T
b1000 !
b1000 +
0H
0M
bz100 ,
0R
04
0>
b100 /
1<
b0 -
0C
0D
0I
0N
06
00
05
1:
0?
b0 &
b0 *
b0 $
b0 (
b100 #
b100 '
#600
1e
0`
b10 [
0j
1"
1a
1K
b101 !
b101 +
1H
0^
0g
1l
1k
1E
b1000 Y
0M
bz000 ,
0W
b1010 .
b1010 X
1U
1J
14
b1100 /
1A
b11 -
19
1I
1S
18
0=
1B
11
1;
1?
b1010 &
b1010 *
b1010 %
b1010 )
b101 $
b101 (
b1100 #
b1100 '
#700
1m
b100 \
1h
0j
1f
1P
1"
0`
0e
1g
b1 !
b1 +
b0 [
0n
1W
0^
0a
1Q
0l
b1100 .
b1100 X
0K
17
1T
b100 Y
bz100 ,
0M
0J
1O
1C
b110 /
0A
09
b1101 -
1>
0I
08
1=
01
16
10
15
0?
b1000 &
b1000 *
b1100 %
b1100 )
b110 $
b110 (
b111 #
b111 '
#800
1j
1i
1c
1d
b111 \
1_
1e
1a
b1110 [
1n
1K
1]
1^
1b
1l
b1111 .
b1111 X
1F
1L
b1111 Y
b11100 !
b11100 +
0H
1M
bz111 ,
1R
12
1J
b1111 /
1A
b1111 -
19
1D
1I
1N
13
18
11
1@
1?
b1111 &
b1111 *
b1111 %
b1111 )
b1111 $
b1111 (
b1111 #
b1111 '
