Carry Skip Adder/mux2x1.v
module mux2x1 (
    input [1:0]I, input S, output Y
);
    assign Y = S ? I[1] : I[0];
endmodule

Ripple Carry Adder/fa.v
module fa  (
    input A,B,Cin, output S,C
);
assign S = A^B^Cin;
assign C = (A&B) |(B&Cin) |(A&Cin);
    
endmodule

Carry Select Adder/rca.v
`include "fa.v"
module rca(
    input [3:0] A, input [3:0] B, input Cin, output [3:0] S, output Cout
);
    wire [2:0]C;

    fa M1(.A(A[0]), .B(B[0]), .Cin(Cin), .S(S[0]), .C(C[0]));
    fa M2(.A(A[1]), .B(B[1]), .Cin(C[0]), .S(S[1]), .C(C[1]));
    fa M3(.A(A[2]), .B(B[2]), .Cin(C[1]), .S(S[2]), .C(C[2]));
    fa M4(.A(A[3]), .B(B[3]), .Cin(C[2]), .S(S[3]), .C(Cout));

endmodule

Carry Select Adder/csa.v
`include "rca.v"
`include "mux2x1.v"

module csa (
    input [3:0]A,B, input Cin, output [3:0]S, output Cout
);
    wire [3:0]x,y;
    wire z,w;
    rca M1(.A(A), .B(B), .Cin(1'b0), .S(x), .Cout(z));
    rca M2(.A(A), .B(B), .Cin(1'b1), .S(y), .Cout(w));
    mux2x1 M3(.I({w,z}), .S(Cin), .Y(Cout));

    mux2x1 M4(.I({y[0],x[0]}), .S(Cin), .Y(S[0]));
    mux2x1 M5(.I({y[1],x[1]}), .S(Cin), .Y(S[1]));
    mux2x1 M6(.I({y[2],x[2]}), .S(Cin), .Y(S[2]));
    mux2x1 M7(.I({y[3],x[3]}), .S(Cin), .Y(S[3]));


endmodule

Carry Select Adder/tb.v
module tb;
reg [3:0]A,B;
reg Cin;
wire [3:0]S;
wire Cout;

csa DUT(.A(A), .B(B), .Cin(Cin), .S(S), .Cout(Cout));

integer i,j,k;
initial begin
    $dumpfile("output.vcd");
    $dumpvars(0,tb);

    for(i=0;i<2;i=i+1)
    begin
      for(j=0;j<16;j=j+1)
      begin
        for (k=0;k<16;k=k+1)
        begin
            A = j;
            B = k;
            Cin = i;
            #10;
        end
      end
    end
end
    
endmodule

Carry Select Adder/output.vcd
$date
	Tue Jan 03 18:55:41 2023
$end
$version
	Icarus Verilog
$end
$timescale
	1s
$end
$scope module tb $end
$var wire 4 ! S [3:0] $end
$var wire 1 " Cout $end
$var reg 4 # A [3:0] $end
$var reg 4 $ B [3:0] $end
$var reg 1 % Cin $end
$var integer 32 & i [31:0] $end
$var integer 32 ' j [31:0] $end
$var integer 32 ( k [31:0] $end
$scope module DUT $end
$var wire 4 ) A [3:0] $end
$var wire 4 * B [3:0] $end
$var wire 1 % Cin $end
$var wire 1 + z $end
$var wire 4 , y [3:0] $end
$var wire 4 - x [3:0] $end
$var wire 1 . w $end
$var wire 4 / S [3:0] $end
$var wire 1 " Cout $end
$scope module M1 $end
$var wire 4 0 A [3:0] $end
$var wire 4 1 B [3:0] $end
$var wire 1 2 Cin $end
$var wire 4 3 S [3:0] $end
$var wire 1 + Cout $end
$var wire 3 4 C [2:0] $end
$scope module M1 $end
$var wire 1 5 A $end
$var wire 1 6 B $end
$var wire 1 7 C $end
$var wire 1 2 Cin $end
$var wire 1 8 S $end
$upscope $end
$scope module M2 $end
$var wire 1 9 A $end
$var wire 1 : B $end
$var wire 1 ; C $end
$var wire 1 < Cin $end
$var wire 1 = S $end
$upscope $end
$scope module M3 $end
$var wire 1 > A $end
$var wire 1 ? B $end
$var wire 1 @ C $end
$var wire 1 A Cin $end
$var wire 1 B S $end
$upscope $end
$scope module M4 $end
$var wire 1 C A $end
$var wire 1 D B $end
$var wire 1 + C $end
$var wire 1 E Cin $end
$var wire 1 F S $end
$upscope $end
$upscope $end
$scope module M2 $end
$var wire 4 G A [3:0] $end
$var wire 4 H B [3:0] $end
$var wire 1 I Cin $end
$var wire 4 J S [3:0] $end
$var wire 1 . Cout $end
$var wire 3 K C [2:0] $end
$scope module M1 $end
$var wire 1 L A $end
$var wire 1 M B $end
$var wire 1 N C $end
$var wire 1 I Cin $end
$var wire 1 O S $end
$upscope $end
$scope module M2 $end
$var wire 1 P A $end
$var wire 1 Q B $end
$var wire 1 R C $end
$var wire 1 S Cin $end
$var wire 1 T S $end
$upscope $end
$scope module M3 $end
$var wire 1 U A $end
$var wire 1 V B $end
$var wire 1 W C $end
$var wire 1 X Cin $end
$var wire 1 Y S $end
$upscope $end
$scope module M4 $end
$var wire 1 Z A $end
$var wire 1 [ B $end
$var wire 1 . C $end
$var wire 1 \ Cin $end
$var wire 1 ] S $end
$upscope $end
$upscope $end
$scope module M3 $end
$var wire 2 ^ I [1:0] $end
$var wire 1 % S $end
$var wire 1 " Y $end
$upscope $end
$scope module M4 $end
$var wire 2 _ I [1:0] $end
$var wire 1 % S $end
$var wire 1 ` Y $end
$upscope $end
$scope module M5 $end
$var wire 2 a I [1:0] $end
$var wire 1 % S $end
$var wire 1 b Y $end
$upscope $end
$scope module M6 $end
$var wire 2 c I [1:0] $end
$var wire 1 % S $end
$var wire 1 d Y $end
$upscope $end
$scope module M7 $end
$var wire 2 e I [1:0] $end
$var wire 1 % S $end
$var wire 1 f Y $end
$upscope $end
$upscope $end
$upscope $end
$enddefinitions $end
$comment Show the parameter values. $end
$dumpall
$end
#0
$dumpvars
0f
b0 e
0d
b0 c
0b
b0 a
0`
b10 _
b0 ^
0]
0\
0[
0Z
0Y
0X
0W
0V
0U
0T
0S
0R
0Q
0P
1O
0N
0M
0L
b0 K
b1 J
1I
b0 H
b0 G
0F
0E
0D
0C
0B
0A
0@
0?
0>
0=
0<
0;
0:
09
08
07
06
05
b0 4
b0 3
02
b0 1
b0 0
b0 /
0.
b0 -
b1 ,
0+
b0 *
b0 )
b0 (
b0 '
b0 &
0%
b0 $
b0 #
0"
b0 !
$end
#10
b10 a
b1 !
b1 /
1`
1T
1S
b1 _
b1 K
1N
b1 -
b1 3
18
b10 ,
b10 J
0O
16
1M
b1 $
b1 *
b1 1
b1 H
b1 (
#20
b0 c
0`
b10 !
b10 /
1b
0Y
0S
0X
b10 _
0N
b11 a
b0 K
0R
08
b10 -
b10 3
1=
1O
b11 ,
b11 J
1T
06
1:
0M
1Q
b10 $
b10 *
b10 1
b10 H
b10 (
#30
b10 c
1Y
1X
1R
b1 a
b11 !
b11 /
1`
0T
1S
b1 _
b11 K
1N
b11 -
b11 3
18
b100 ,
b100 J
0O
16
1M
b11 $
b11 *
b11 1
b11 H
b11 (
#40
b0 e
0`
0b
b100 !
b100 /
1d
0]
0S
0X
0\
b10 _
0N
b0 a
0R
b11 c
b0 K
0W
08
0=
b100 -
b100 3
1B
1O
0T
b101 ,
b101 J
1Y
06
0:
1?
0M
0Q
1V
b100 $
b100 *
b100 1
b100 H
b100 (
#50
b10 a
b101 !
b101 /
1`
1T
1S
b1 _
b1 K
1N
b101 -
b101 3
18
b110 ,
b110 J
0O
16
1M
b101 $
b101 *
b101 1
b101 H
b101 (
#60
b0 e
0]
0\
0W
b11 c
0`
b110 !
b110 /
1b
1Y
0S
0X
b10 _
0N
b11 a
b0 K
0R
08
b110 -
b110 3
1=
1O
b111 ,
b111 J
1T
06
1:
0M
1Q
b110 $
b110 *
b110 1
b110 H
b110 (
#70
b10 e
1]
1\
1W
b1 c
0Y
1X
1R
b1 a
b111 !
b111 /
1`
0T
1S
b1 _
b111 K
1N
b111 -
b111 3
18
b1000 ,
b1000 J
0O
16
1M
b111 $
b111 *
b111 1
b111 H
b111 (
#80
0`
0b
0d
b1000 !
b1000 /
1f
0S
0X
0\
b10 _
0N
b0 a
0R
b0 c
b0 K
0W
b11 e
b0 ^
0.
08
0=
0B
b1000 -
b1000 3
1F
1O
0T
0Y
b1001 ,
b1001 J
1]
06
0:
0?
1D
0M
0Q
0V
1[
b1000 $
b1000 *
b1000 1
b1000 H
b1000 (
#90
b10 a
b1001 !
b1001 /
1`
1T
1S
b1 _
b1 K
1N
b1001 -
b1001 3
18
b1010 ,
b1010 J
0O
16
1M
b1001 $
b1001 *
b1001 1
b1001 H
b1001 (
#100
b0 c
0`
b1010 !
b1010 /
1b
0Y
0S
0X
b10 _
0N
b11 a
b0 K
0R
08
b1010 -
b1010 3
1=
1O
b1011 ,
b1011 J
1T
06
1:
0M
1Q
b1010 $
b1010 *
b1010 1
b1010 H
b1010 (
#110
b10 c
1Y
1X
1R
b1 a
b1011 !
b1011 /
1`
0T
1S
b1 _
b11 K
1N
b1011 -
b1011 3
18
b1100 ,
b1100 J
0O
16
1M
b1011 $
b1011 *
b1011 1
b1011 H
b1011 (
#120
b0 ^
0.
b11 e
0`
0b
b1100 !
b1100 /
1d
1]
0S
0X
0\
b10 _
0N
b0 a
0R
b11 c
b0 K
0W
08
0=
b1100 -
b1100 3
1B
1O
0T
b1101 ,
b1101 J
1Y
06
0:
1?
0M
0Q
1V
b1100 $
b1100 *
b1100 1
b1100 H
b1100 (
#130
b10 a
b1101 !
b1101 /
1`
1T
1S
b1 _
b1 K
1N
b1101 -
b1101 3
18
b1110 ,
b1110 J
0O
16
1M
b1101 $
b1101 *
b1101 1
b1101 H
b1101 (
#140
b0 ^
0.
b11 e
1]
0\
0W
b11 c
0`
b1110 !
b1110 /
1b
1Y
0S
0X
b10 _
0N
b11 a
b0 K
0R
08
b1110 -
b1110 3
1=
1O
b1111 ,
b1111 J
1T
06
1:
0M
1Q
b1110 $
b1110 *
b1110 1
b1110 H
b1110 (
#150
b10 ^
1.
b1 e
0]
1\
1W
b1 c
0Y
1X
1R
b1 a
b1111 !
b1111 /
1`
0T
1S
b1 _
b111 K
1N
b1111 -
b1111 3
18
b0 ,
b0 J
0O
16
1M
b1111 $
b1111 *
b1111 1
b1111 H
b1111 (
#160
0b
0d
b1 !
b1 /
0f
0X
0\
b10 a
0R
b0 c
b1 K
0W
b0 e
b0 ^
0.
0=
0B
b1 -
b1 3
0F
1T
0Y
b10 ,
b10 J
0]
06
0:
0?
0D
0M
0Q
0V
0[
15
1L
b0 $
b0 *
b0 1
b0 H
b1 #
b1 )
b1 0
b1 G
b1 '
b0 (
#170
1b
b11 a
b10 !
b10 /
0`
1=
1<
b1 4
17
b10 _
b10 -
b10 3
08
b11 ,
b11 J
1O
16
1M
b1 $
b1 *
b1 1
b1 H
b1 (
#180
0d
b10 c
1`
b11 !
b11 /
1b
0B
1Y
0<
0A
1X
07
b0 4
0;
b1 _
b1 a
b11 K
1R
18
b11 -
b11 3
1=
0O
b100 ,
b100 J
0T
06
1:
0M
1Q
b10 $
b10 *
b10 1
b10 H
b10 (
#190
1d
b11 c
1B
0b
1A
1;
b0 a
b100 !
b100 /
0`
0=
1<
b11 4
17
b10 _
b100 -
b100 3
08
b101 ,
b101 J
1O
16
1M
b11 $
b11 *
b11 1
b11 H
b11 (
#200
0f
b0 e
1`
0b
b101 !
b101 /
1d
0F
0]
0<
0A
0E
0X
0\
07
0;
b0 4
0@
b1 _
b10 a
0R
b11 c
b1 K
0W
18
0=
b101 -
b101 3
1B
0O
1T
b110 ,
b110 J
1Y
06
0:
1?
0M
0Q
1V
b100 $
b100 *
b100 1
b100 H
b100 (
#210
1b
b11 a
b110 !
b110 /
0`
1=
1<
b1 4
17
b10 _
b110 -
b110 3
08
b111 ,
b111 J
1O
16
1M
b101 $
b101 *
b101 1
b101 H
b101 (
#220
0f
b10 e
0F
1]
1d
0E
1\
0@
1W
b1 c
1`
b111 !
b111 /
1b
1B
0Y
0<
0A
1X
07
b0 4
0;
b1 _
b1 a
b111 K
1R
18
b111 -
b111 3
1=
0O
b1000 ,
b1000 J
0T
06
1:
0M
1Q
b110 $
b110 *
b110 1
b110 H
b110 (
#230
1f
b11 e
1F
0d
1E
1@
b0 c
0B
0b
1A
1;
b0 a
b1000 !
b1000 /
0`
0=
1<
b111 4
17
b10 _
b1000 -
b1000 3
08
b1001 ,
b1001 J
1O
16
1M
b111 $
b111 *
b111 1
b111 H
b111 (
#240
1`
0b
0d
b1001 !
b1001 /
1f
0"
0<
0A
0E
0X
0\
07
0;
b0 4
0@
0+
b1 _
b10 a
0R
b0 c
b1 K
0W
b11 e
b0 ^
0.
18
0=
0B
b1001 -
b1001 3
1F
0O
1T
0Y
b1010 ,
b1010 J
1]
06
0:
0?
1D
0M
0Q
0V
1[
b1000 $
b1000 *
b1000 1
b1000 H
b1000 (
#250
1b
b11 a
b1010 !
b1010 /
0`
1=
1<
b1 4
17
b10 _
b1010 -
b1010 3
08
b1011 ,
b1011 J
1O
16
1M
b1001 $
b1001 *
b1001 1
b1001 H
b1001 (
#260
0d
b10 c
1`
b1011 !
b1011 /
1b
0B
1Y
0<
0A
1X
07
b0 4
0;
b1 _
b1 a
b11 K
1R
18
b1011 -
b1011 3
1=
0O
b1100 ,
b1100 J
0T
06
1:
0M
1Q
b1010 $
b1010 *
b1010 1
b1010 H
b1010 (
#270
1d
b11 c
1B
0b
1A
1;
b0 a
b1100 !
b1100 /
0`
0=
1<
b11 4
17
b10 _
b1100 -
b1100 3
08
b1101 ,
b1101 J
1O
16
1M
b1011 $
b1011 *
b1011 1
b1011 H
b1011 (
#280
0"
1f
0+
b0 ^
0.
b11 e
1`
0b
b1101 !
b1101 /
1d
1F
1]
0<
0A
0E
0X
0\
07
0;
b0 4
0@
b1 _
b10 a
0R
b11 c
b1 K
0W
18
0=
b1101 -
b1101 3
1B
0O
1T
b1110 ,
b1110 J
1Y
06
0:
1?
0M
0Q
1V
b1100 $
b1100 *
b1100 1
b1100 H
b1100 (
#290
1b
b11 a
b1110 !
b1110 /
0`
1=
1<
b1 4
17
b10 _
b1110 -
b1110 3
08
b1111 ,
b1111 J
1O
16
1M
b1101 $
b1101 *
b1101 1
b1101 H
b1101 (
#300
0"
1f
0+
b10 ^
1.
b1 e
1F
0]
1d
0E
1\
0@
1W
b1 c
1`
b1111 !
b1111 /
1b
1B
0Y
0<
0A
1X
07
b0 4
0;
b1 _
b1 a
b111 K
1R
18
b1111 -
b1111 3
1=
0O
b0 ,
b0 J
0T
06
1:
0M
1Q
b1110 $
b1110 *
b1110 1
b1110 H
b1110 (
#310
1"
0f
b11 ^
1+
b0 e
0F
0d
1E
1@
b0 c
0B
0b
1A
1;
b0 a
b0 !
b0 /
0`
0=
1<
b111 4
17
b10 _
b0 -
b0 3
08
b1 ,
b1 J
1O
16
1M
b1111 $
b1111 *
b1111 1
b1111 H
b1111 (
#320
1b
0A
0X
0;
b11 a
0R
0d
b10 !
b10 /
0f
0"
1=
1T
0E
0\
0<
0S
0@
0+
b0 c
0W
b0 e
b0 ^
0.
b0 4
07
b0 K
0N
0B
b10 -
b10 3
0F
0Y
b11 ,
b11 J
0]
06
0:
0?
0D
0M
0Q
0V
0[
05
19
0L
1P
b0 $
b0 *
b0 1
b0 H
b10 #
b10 )
b10 0
b10 G
b10 '
b0 (
#330
b10 c
1Y
1X
b1 a
1R
b11 !
b11 /
1`
0T
1S
b1 _
b11 K
1N
b11 -
b11 3
18
b100 ,
b100 J
0O
16
1M
b1 $
b1 *
b1 1
b1 H
b1 (
#340
1d
b11 c
0`
b100 !
b100 /
0b
1B
1A
0S
b10 4
1;
b10 _
b10 K
0N
b0 a
08
b100 -
b100 3
0=
1O
b101 ,
b101 J
0T
06
1:
0M
1Q
b10 $
b10 *
b10 1
b10 H
b10 (
#350
b10 a
b101 !
b101 /
1`
1T
1S
b1 _
b11 K
1N
b101 -
b101 3
18
b110 ,
b110 J
0O
16
1M
b11 $
b11 *
b11 1
b11 H
b11 (
#360
0f
0X
0R
b0 e
0`
1b
b110 !
b110 /
1d
0F
0]
0A
0E
0S
0\
0;
b0 4
0@
b10 _
0N
b11 a
b11 c
b0 K
0W
08
1=
b110 -
b110 3
1B
1O
1T
b111 ,
b111 J
1Y
06
0:
1?
0M
0Q
1V
b100 $
b100 *
b100 1
b100 H
b100 (
#370
b10 e
1]
1\
1W
b1 c
0Y
1X
b1 a
1R
b111 !
b111 /
1`
0T
1S
b1 _
b111 K
1N
b111 -
b111 3
18
b1000 ,
b1000 J
0O
16
1M
b101 $
b101 *
b101 1
b101 H
b101 (
#380
1f
b11 e
1F
0d
1E
1@
b0 c
0`
b1000 !
b1000 /
0b
0B
1A
0S
b110 4
1;
b10 _
b110 K
0N
b0 a
08
b1000 -
b1000 3
0=
1O
b1001 ,
b1001 J
0T
06
1:
0M
1Q
b110 $
b110 *
b110 1
b110 H
b110 (
#390
b10 a
b1001 !
b1001 /
1`
1T
1S
b1 _
b111 K
1N
b1001 -
b1001 3
18
b1010 ,
b1010 J
0O
16
1M
b111 $
b111 *
b111 1
b111 H
b111 (
#400
0X
0R
0`
1b
0d
b1010 !
b1010 /
1f
0"
0A
0E
0S
0\
0;
b0 4
0@
0+
b10 _
0N
b11 a
b0 c
b0 K
0W
b11 e
b0 ^
0.
08
1=
0B
b1010 -
b1010 3
1F
1O
1T
0Y
b1011 ,
b1011 J
1]
06
0:
0?
1D
0M
0Q
0V
1[
b1000 $
b1000 *
b1000 1
b1000 H
b1000 (
#410
b10 c
1Y
1X
b1 a
1R
b1011 !
b1011 /
1`
0T
1S
b1 _
b11 K
1N
b1011 -
b1011 3
18
b1100 ,
b1100 J
0O
16
1M
b1001 $
b1001 *
b1001 1
b1001 H
b1001 (
#420
1d
b11 c
0`
b1100 !
b1100 /
0b
1B
1A
0S
b10 4
1;
b10 _
b10 K
0N
b0 a
08
b1100 -
b1100 3
0=
1O
b1101 ,
b1101 J
0T
06
1:
0M
1Q
b1010 $
b1010 *
b1010 1
b1010 H
b1010 (
#430
b10 a
b1101 !
b1101 /
1`
1T
1S
b1 _
b11 K
1N
b1101 -
b1101 3
18
b1110 ,
b1110 J
0O
16
1M
b1011 $
b1011 *
b1011 1
b1011 H
b1011 (
#440
0"
1f
0+
0X
b0 ^
0.
0R
b11 e
0`
1b
b1110 !
b1110 /
1d
1F
1]
0A
0E
0S
0\
0;
b0 4
0@
b10 _
0N
b11 a
b11 c
b0 K
0W
08
1=
b1110 -
b1110 3
1B
1O
1T
b1111 ,
b1111 J
1Y
06
0:
1?
0M
0Q
1V
b1100 $
b1100 *
b1100 1
b1100 H
b1100 (
#450
b10 ^
1.
b1 e
0]
1\
1W
b1 c
0Y
1X
b1 a
1R
b1111 !
b1111 /
1`
0T
1S
b1 _
b111 K
1N
b1111 -
b1111 3
18
b0 ,
b0 J
0O
16
1M
b1101 $
b1101 *
b1101 1
b1101 H
b1101 (
#460
1"
0f
b11 ^
1+
b0 e
0F
0d
1E
1@
b0 c
0`
b0 !
b0 /
0b
0B
1A
0S
b110 4
1;
b10 _
b110 K
0N
b0 a
08
b0 -
b0 3
0=
1O
b1 ,
b1 J
0T
06
1:
0M
1Q
b1110 $
b1110 *
b1110 1
b1110 H
b1110 (
#470
b10 a
b1 !
b1 /
1`
1T
1S
b1 _
b111 K
1N
b1 -
b1 3
18
b10 ,
b10 J
0O
16
1M
b1111 $
b1111 *
b1111 1
b1111 H
b1111 (
#480
1b
0d
b11 !
b11 /
0f
0"
0A
0E
0\
0;
b0 4
0@
0+
b1 a
b10 c
b11 K
0W
b0 e
b0 ^
0.
1=
0B
b11 -
b11 3
0F
0T
1Y
b100 ,
b100 J
0]
06
0:
0?
0D
0M
0Q
0V
0[
15
1L
b0 $
b0 *
b0 1
b0 H
b11 #
b11 )
b11 0
b11 G
b11 '
b0 (
#490
1d
b11 c
0b
1B
1A
b0 a
1;
b100 !
b100 /
0`
0=
1<
b11 4
17
b10 _
b100 -
b100 3
08
b101 ,
b101 J
1O
16
1M
b1 $
b1 *
b1 1
b1 H
b1 (
#500
1`
b101 !
b101 /
0b
0<
b10 4
07
b1 _
b10 a
18
b101 -
b101 3
0=
0O
b110 ,
b110 J
1T
06
1:
0M
1Q
b10 $
b10 *
b10 1
b10 H
b10 (
#510
1b
b11 a
b110 !
b110 /
0`
1=
1<
b11 4
17
b10 _
b110 -
b110 3
08
b111 ,
b111 J
1O
16
1M
b11 $
b11 *
b11 1
b11 H
b11 (
#520
0f
0A
0;
b10 e
1`
1b
b111 !
b111 /
1d
0F
1]
0<
0E
1\
07
b0 4
0@
b1 _
b1 a
b1 c
b111 K
1W
18
1=
b111 -
b111 3
1B
0O
0T
b1000 ,
b1000 J
0Y
06
0:
1?
0M
0Q
1V
b100 $
b100 *
b100 1
b100 H
b100 (
#530
1f
b11 e
1F
0d
1E
1@
b0 c
0b
0B
1A
b0 a
1;
b1000 !
b1000 /
0`
0=
1<
b111 4
17
b10 _
b1000 -
b1000 3
08
b1001 ,
b1001 J
1O
16
1M
b101 $
b101 *
b101 1
b101 H
b101 (
#540
1`
b1001 !
b1001 /
0b
0<
b110 4
07
b1 _
b10 a
18
b1001 -
b1001 3
0=
0O
b1010 ,
b1010 J
1T
06
1:
0M
1Q
b110 $
b110 *
b110 1
b110 H
b110 (
#550
1b
b11 a
b1010 !
b1010 /
0`
1=
1<
b111 4
17
b10 _
b1010 -
b1010 3
08
b1011 ,
b1011 J
1O
16
1M
b111 $
b111 *
b111 1
b111 H
b111 (
#560
0A
0;
1`
1b
0d
b1011 !
b1011 /
1f
0"
0<
0E
0\
07
b0 4
0@
0+
b1 _
b1 a
b10 c
b11 K
0W
b11 e
b0 ^
0.
18
1=
0B
b1011 -
b1011 3
1F
0O
0T
1Y
b1100 ,
b1100 J
1]
06
0:
0?
1D
0M
0Q
0V
1[
b1000 $
b1000 *
b1000 1
b1000 H
b1000 (
#570
1d
b11 c
0b
1B
1A
b0 a
1;
b1100 !
b1100 /
0`
0=
1<
b11 4
17
b10 _
b1100 -
b1100 3
08
b1101 ,
b1101 J
1O
16
1M
b1001 $
b1001 *
b1001 1
b1001 H
b1001 (
#580
1`
b1101 !
b1101 /
0b
0<
b10 4
07
b1 _
b10 a
18
b1101 -
b1101 3
0=
0O
b1110 ,
b1110 J
1T
06
1:
0M
1Q
b1010 $
b1010 *
b1010 1
b1010 H
b1010 (
#590
1b
b11 a
b1110 !
b1110 /
0`
1=
1<
b11 4
17
b10 _
b1110 -
b1110 3
08
b1111 ,
b1111 J
1O
16
1M
b1011 $
b1011 *
b1011 1
b1011 H
b1011 (
#600
0"
1f
0A
0+
b10 ^
1.
0;
b1 e
1`
1b
b1111 !
b1111 /
1d
1F
0]
0<
0E
1\
07
b0 4
0@
b1 _
b1 a
b1 c
b111 K
1W
18
1=
b1111 -
b1111 3
1B
0O
0T
b0 ,
b0 J
0Y
06
0:
1?
0M
0Q
1V
b1100 $
b1100 *
b1100 1
b1100 H
b1100 (
#610
1"
0f
b11 ^
1+
b0 e
0F
0d
1E
1@
b0 c
0b
0B
1A
b0 a
1;
b0 !
b0 /
0`
0=
1<
b111 4
17
b10 _
b0 -
b0 3
08
b1 ,
b1 J
1O
16
1M
b1101 $
b1101 *
b1101 1
b1101 H
b1101 (
#620
1`
b1 !
b1 /
0b
0<
b110 4
07
b1 _
b10 a
18
b1 -
b1 3
0=
0O
b10 ,
b10 J
1T
06
1:
0M
1Q
b1110 $
b1110 *
b1110 1
b1110 H
b1110 (
#630
1b
b11 a
b10 !
b10 /
0`
1=
1<
b111 4
17
b10 _
b10 -
b10 3
08
b11 ,
b11 J
1O
16
1M
b1111 $
b1111 *
b1111 1
b1111 H
b1111 (
#640
0b
1d
0E
0\
0@
b0 a
b11 c
0W
b100 !
b100 /
0f
0"
0=
1B
0T
1Y
0<
0A
0S
0X
0+
b0 e
b0 ^
0.
07
b0 4
0;
0N
b0 K
0R
b100 -
b100 3
0F
b101 ,
b101 J
0]
06
0:
0?
0D
0M
0Q
0V
0[
05
09
1>
0L
0P
1U
b0 $
b0 *
b0 1
b0 H
b100 #
b100 )
b100 0
b100 G
b100 '
b0 (
#650
b10 a
b101 !
b101 /
1`
1T
1S
b1 _
b1 K
1N
b101 -
b101 3
18
b110 ,
b110 J
0O
16
1M
b1 $
b1 *
b1 1
b1 H
b1 (
#660
b0 e
0]
0\
b11 c
0W
0`
b110 !
b110 /
1b
1Y
0S
0X
b10 _
0N
b11 a
b0 K
0R
08
b110 -
b110 3
1=
1O
b111 ,
b111 J
1T
06
1:
0M
1Q
b10 $
b10 *
b10 1
b10 H
b10 (
#670
b10 e
1]
1\
b1 c
1W
0Y
1X
1R
b1 a
b111 !
b111 /
1`
0T
1S
b1 _
b111 K
1N
b111 -
b111 3
18
b1000 ,
b1000 J
0O
16
1M
b11 $
b11 *
b11 1
b11 H
b11 (
#680
1f
b11 e
0`
0b
b1000 !
b1000 /
0d
1F
1E
0S
0X
b100 4
1@
b10 _
0N
b0 a
b100 K
0R
b0 c
08
0=
b1000 -
b1000 3
0B
1O
0T
b1001 ,
b1001 J
0Y
06
0:
1?
0M
0Q
1V
b100 $
b100 *
b100 1
b100 H
b100 (
#690
b10 a
b1001 !
b1001 /
1`
1T
1S
b1 _
b101 K
1N
b1001 -
b1001 3
18
b1010 ,
b1010 J
0O
16
1M
b101 $
b101 *
b101 1
b101 H
b101 (
#700
b0 c
0`
b1010 !
b1010 /
1b
0Y
0S
0X
b10 _
0N
b11 a
b100 K
0R
08
b1010 -
b1010 3
1=
1O
b1011 ,
b1011 J
1T
06
1:
0M
1Q
b110 $
b110 *
b110 1
b110 H
b110 (
#710
b10 c
1Y
1X
1R
b1 a
b1011 !
b1011 /
1`
0T
1S
b1 _
b111 K
1N
b1011 -
b1011 3
18
b1100 ,
b1100 J
0O
16
1M
b111 $
b111 *
b111 1
b111 H
b111 (
#720
0\
0W
0`
0b
1d
b1100 !
b1100 /
1f
0"
0E
0S
0X
b0 4
0@
0+
b10 _
0N
b0 a
b0 K
0R
b11 c
b11 e
b0 ^
0.
08
0=
1B
b1100 -
b1100 3
1F
1O
0T
1Y
b1101 ,
b1101 J
1]
06
0:
0?
1D
0M
0Q
0V
1[
b1000 $
b1000 *
b1000 1
b1000 H
b1000 (
#730
b10 a
b1101 !
b1101 /
1`
1T
1S
b1 _
b1 K
1N
b1101 -
b1101 3
18
b1110 ,
b1110 J
0O
16
1M
b1001 $
b1001 *
b1001 1
b1001 H
b1001 (
#740
b0 ^
0.
b11 e
1]
0\
b11 c
0W
0`
b1110 !
b1110 /
1b
1Y
0S
0X
b10 _
0N
b11 a
b0 K
0R
08
b1110 -
b1110 3
1=
1O
b1111 ,
b1111 J
1T
06
1:
0M
1Q
b1010 $
b1010 *
b1010 1
b1010 H
b1010 (
#750
b10 ^
1.
b1 e
0]
1\
b1 c
1W
0Y
1X
1R
b1 a
b1111 !
b1111 /
1`
0T
1S
b1 _
b111 K
1N
b1111 -
b1111 3
18
b0 ,
b0 J
0O
16
1M
b1011 $
b1011 *
b1011 1
b1011 H
b1011 (
#760
1"
0f
b11 ^
1+
b0 e
0`
0b
b0 !
b0 /
0d
0F
1E
0S
0X
b100 4
1@
b10 _
0N
b0 a
b100 K
0R
b0 c
08
0=
b0 -
b0 3
0B
1O
0T
b1 ,
b1 J
0Y
06
0:
1?
0M
0Q
1V
b1100 $
b1100 *
b1100 1
b1100 H
b1100 (
#770
b10 a
b1 !
b1 /
1`
1T
1S
b1 _
b101 K
1N
b1 -
b1 3
18
b10 ,
b10 J
0O
16
1M
b1101 $
b1101 *
b1101 1
b1101 H
b1101 (
#780
b0 c
0`
b10 !
b10 /
1b
0Y
0S
0X
b10 _
0N
b11 a
b100 K
0R
08
b10 -
b10 3
1=
1O
b11 ,
b11 J
1T
06
1:
0M
1Q
b1110 $
b1110 *
b1110 1
b1110 H
b1110 (
#790
b10 c
1Y
1X
1R
b1 a
b11 !
b11 /
1`
0T
1S
b1 _
b111 K
1N
b11 -
b11 3
18
b100 ,
b100 J
0O
16
1M
b1111 $
b1111 *
b1111 1
b1111 H
b1111 (
#800
0\
0W
0b
1d
b101 !
b101 /
0f
0"
0E
0X
b0 4
0@
0+
b10 a
b1 K
0R
b11 c
b0 e
b0 ^
0.
0=
1B
b101 -
b101 3
0F
1T
1Y
b110 ,
b110 J
0]
06
0:
0?
0D
0M
0Q
0V
0[
15
1L
b0 $
b0 *
b0 1
b0 H
b101 #
b101 )
b101 0
b101 G
b101 '
b0 (
#810
1b
b11 a
b110 !
b110 /
0`
1=
1<
b1 4
17
b10 _
b110 -
b110 3
08
b111 ,
b111 J
1O
16
1M
b1 $
b1 *
b1 1
b1 H
b1 (
#820
0f
b10 e
1d
0F
1]
0E
1\
0@
b1 c
1W
1`
b111 !
b111 /
1b
1B
0Y
0<
0A
1X
07
b0 4
0;
b1 _
b1 a
b111 K
1R
18
b111 -
b111 3
1=
0O
b1000 ,
b1000 J
0T
06
1:
0M
1Q
b10 $
b10 *
b10 1
b10 H
b10 (
#830
1f
b11 e
0d
1F
1E
b0 c
1@
0B
0b
1A
1;
b0 a
b1000 !
b1000 /
0`
0=
1<
b111 4
17
b10 _
b1000 -
b1000 3
08
b1001 ,
b1001 J
1O
16
1M
b11 $
b11 *
b11 1
b11 H
b11 (
#840
1`
0b
b1001 !
b1001 /
0d
0<
0A
0X
07
b100 4
0;
b1 _
b10 a
b101 K
0R
b0 c
18
0=
b1001 -
b1001 3
0B
0O
1T
b1010 ,
b1010 J
0Y
06
0:
1?
0M
0Q
1V
b100 $
b100 *
b100 1
b100 H
b100 (
#850
1b
b11 a
b1010 !
b1010 /
0`
1=
1<
b101 4
17
b10 _
b1010 -
b1010 3
08
b1011 ,
b1011 J
1O
16
1M
b101 $
b101 *
b101 1
b101 H
b101 (
#860
0d
b10 c
1`
b1011 !
b1011 /
1b
0B
1Y
0<
0A
1X
07
b100 4
0;
b1 _
b1 a
b111 K
1R
18
b1011 -
b1011 3
1=
0O
b1100 ,
b1100 J
0T
06
1:
0M
1Q
b110 $
b110 *
b110 1
b110 H
b110 (
